{
  "libros": [
    {
      "nombre": "la casa de papel",
      "precio": "24",
      "id": 4
    },
    {
      "nombre": "La casa de papel",
      "precio": "34",
      "id": 5
    },
    {
      "nombre": "101 dalmatas",
      "precio": "23",
      "id": 6
    },
    {
      "nombre": "ToysTory",
      "precio": "13",
      "id": 7
    },
    {
      "nombre": "Blanca Nieve",
      "precio": "23",
      "id": 8
    },
    {
      "nombre": "Pinocho",
      "precio": "45",
      "id": 9
    },
    {
      "nombre": "ca",
      "precio": "ca",
      "id": 10
    },
    {
      "nombre": "casa",
      "precio": "23",
      "id": 11
    },
    {
      "nombre": "casa",
      "precio": "234",
      "id": 12
    }
  ]
}